off_your_rocker/__init__.py
off_your_rocker/capabilities.py
off_your_rocker/colcon.py
off_your_rocker/mount.py
off_your_rocker/run_arg.py
off_your_rocker/spacenav.py
off_your_rocker/templates/colcon_snippet.Dockerfile.em
off_your_rocker/templates/spacenav_snippet.Dockerfile.em
off_your_rocker-0.1.0.dist-info/METADATA
off_your_rocker-0.1.0.dist-info/WHEEL
off_your_rocker-0.1.0.dist-info/entry_points.txt
off_your_rocker-0.1.0.dist-info/top_level.txt
off_your_rocker-0.1.0.dist-info/RECORD
