Metadata-Version: 2.1
Name: off-your-rocker
Version: 0.1.0
Summary: Extra plugins for rocker
Home-page: https://github.com/sloretz/off-your-rocker
Author: Shane Loretz
Author-email: shane.loretz@gmail.com
License: Apache 2.0
Platform: UNKNOWN
Requires-Dist: rocker
